fernet_encrypt/__init__.py
fernet_encrypt/__main__.py
fernet_encrypt/__version__.py
fernet_encrypt/app.py
fernet_encrypt/commands.py
fernet_encrypt/keys/.gitignore
fernet_encrypt/utils.py
fernet_encrypt-2.0.0.dist-info/LICENSE.md
fernet_encrypt-2.0.0.dist-info/METADATA
fernet_encrypt-2.0.0.dist-info/WHEEL
fernet_encrypt-2.0.0.dist-info/entry_points.txt
fernet_encrypt-2.0.0.dist-info/RECORD
