Metadata-Version: 2.3
Name: fernet-encrypt
Version: 2.0.0
Summary: Fernet Encryption CLI tool
License: MIT
Author: Tyson Holub
Author-email: tyson@tysonholub.com
Requires-Python: >=3.10,<4.0
Classifier: License :: OSI Approved :: MIT License
Classifier: Programming Language :: Python :: 3
Classifier: Programming Language :: Python :: 3.10
Classifier: Programming Language :: Python :: 3.11
Classifier: Programming Language :: Python :: 3.12
Classifier: Programming Language :: Python :: 3.13
Requires-Dist: cryptography (>=39.0.2,<40.0.0)
Requires-Dist: python-socketio (>=5.12.1,<6.0.0)
Requires-Dist: requests (>=2.32.3,<3.0.0)
Requires-Dist: typer (>=0.13,<0.14)
Requires-Dist: websocket-client (>=1.8.0,<2.0.0)
